excelParse/FastqToFC.py
excelParse/ParserXLS.py
excelParse/YamlFileOperate.py
excelParse/__init__.py
excelParse/common_functions.py
excelParse/geo_common.py
excelParse/upload.py
excelParse-1.3.1.dist-info/METADATA
excelParse-1.3.1.dist-info/WHEEL
excelParse-1.3.1.dist-info/top_level.txt
excelParse-1.3.1.dist-info/RECORD
