Metadata-Version: 2.1
Name: excelParse
Version: 1.3.1
Summary: Used for KCmetadata.xls Parsing
Home-page: https://gitee.com/ganjun87/excel-parse.git
Author: ganjun
Author-email: ganjun@alumni.hust.edu.cn
License: MIT License
Keywords: pip,excelParse
Platform: any
Requires-Python: >=3
Requires-Dist: xlrd
